sasefied/__init__.py
sasefied/core.py
sasefied-0.1.3.dist-info/METADATA
sasefied-0.1.3.dist-info/WHEEL
sasefied-0.1.3.dist-info/top_level.txt
sasefied-0.1.3.dist-info/RECORD
