Metadata-Version: 2.4
Name: sasefied
Version: 0.1.3
Summary: Sasefied is an agentic systems platform for building multi-agent workflows across industries
Author: Sasefied Inc.
Maintainer-email: Satyam Singh <satyamsingh7734@gmail.com>
License-Expression: MIT
Project-URL: Homepage, https://github.com/Sasefied/Sasefied_orchestra_lib.git
Project-URL: Repository, https://github.com/Sasefied/Sasefied_orchestra_lib.git
Project-URL: Issues, https://github.com/Sasefied/Sasefied_orchestra_lib.git/issues
Keywords: agentic-systems,multi-agent,ai-orchestration,langgraph,crewai,fastapi,workflow-engine,industry-ai
Classifier: Development Status :: 3 - Alpha
Classifier: Intended Audience :: Developers
Classifier: Programming Language :: Python :: 3.11
Classifier: Programming Language :: Python :: 3.12
Classifier: Topic :: Software Development :: Libraries :: Python Modules
Classifier: Topic :: Scientific/Engineering :: Artificial Intelligence
Requires-Python: >=3.10
Requires-Dist: langchain-core
Requires-Dist: langgraph>=0.2.0
Requires-Dist: langchain-community
Requires-Dist: requests
Requires-Dist: duckduckgo-search>=3.0.0
Requires-Dist: websockets
Requires-Dist: sseclient-py
Provides-Extra: dev
Requires-Dist: pytest>=8.0; extra == "dev"
Requires-Dist: pytest-asyncio>=0.23; extra == "dev"
Requires-Dist: black>=24.0; extra == "dev"
Requires-Dist: ruff>=0.3.0; extra == "dev"
Requires-Dist: mypy>=1.8; extra == "dev"
Requires-Dist: pre-commit>=3.6; extra == "dev"
Provides-Extra: docs
Requires-Dist: mkdocs>=1.5; extra == "docs"
Requires-Dist: mkdocs-material>=9.5; extra == "docs"
